debugwand/__init__.py
debugwand/attacher.py
debugwand/cli.py
debugwand/container.py
debugwand/debugpy_template.py
debugwand/kubernetes.py
debugwand/operations.py
debugwand/types.py
debugwand/ui.py
debugwand-0.4.2.dist-info/METADATA
debugwand-0.4.2.dist-info/WHEEL
debugwand-0.4.2.dist-info/entry_points.txt
debugwand-0.4.2.dist-info/licenses/LICENSE
debugwand-0.4.2.dist-info/RECORD
