Metadata-Version: 2.4
Name: debugwand
Version: 0.4.2
Summary: A zero-preparation remote debugger for Python applications running in Kubernetes clusters or Docker containers.
Project-URL: Homepage, https://github.com/savannahostrowski/debugwand
Project-URL: Repository, https://github.com/savannahostrowski/debugwand
Project-URL: Issues, https://github.com/savannahostrowski/debugwand/issues
License-File: LICENSE
Keywords: debugger,debugging,kubernetes
Classifier: Development Status :: 3 - Alpha
Classifier: Environment :: Console
Classifier: Intended Audience :: Developers
Classifier: License :: OSI Approved :: MIT License
Classifier: Operating System :: MacOS
Classifier: Operating System :: Microsoft :: Windows
Classifier: Operating System :: POSIX :: Linux
Classifier: Programming Language :: Python :: 3
Classifier: Programming Language :: Python :: 3.14
Classifier: Topic :: System :: Monitoring
Classifier: Topic :: Utilities
Requires-Python: >=3.14.0
Requires-Dist: debugpy>=1.8.17
Requires-Dist: rich>=13.9.4
Requires-Dist: typer>=0.20.0
